light_process/__init__.py
light_process/__meta__.py
light_process/utils.py
light_process/__pycache__/__init__.cpython-36.pyc
light_process/__pycache__/__init__.cpython-38.pyc
light_process/__pycache__/__meta__.cpython-36.pyc
light_process/__pycache__/__meta__.cpython-38.pyc
light_process/__pycache__/utils.cpython-36.pyc
light_process/__pycache__/utils.cpython-38.pyc
light_process-0.0.7.dist-info/LICENSE
light_process-0.0.7.dist-info/METADATA
light_process-0.0.7.dist-info/WHEEL
light_process-0.0.7.dist-info/top_level.txt
light_process-0.0.7.dist-info/RECORD
