Metadata-Version: 2.1
Name: light-process
Version: 0.0.7
Summary: Python multiprocessing.Process that does not need to import __main__.
Home-page: https://github.com/justengel/light_process
Author: Justin Engel
Author-email: jtengel08@gmail.com
License: MIT
Download-URL: https://github.com/justengel/light_process/archive/v0.0.7.tar.gz
Keywords: Light Process
Platform: any
Classifier: Programming Language :: Python
Classifier: Programming Language :: Python :: 3
Classifier: Operating System :: OS Independent
